mass_sight/__init__.py
mass_sight/__init__.pyi
mass_sight/assignment_sampling.py
mass_sight/cli.py
mass_sight/lcms_utils.py
mass_sight/matcher.py
mass_sight/multistudy.py
mass_sight/py.typed
mass_sight/structure_graph.py
mass_sight-0.1.0.dist-info/WHEEL
mass_sight-0.1.0.dist-info/entry_points.txt
mass_sight-0.1.0.dist-info/METADATA
mass_sight-0.1.0.dist-info/RECORD
