Metadata-Version: 2.3
Name: mass-sight
Version: 0.1.0
Summary: Probabilistic drift-aware optimal transport for cross-study LC–MS feature matching
Keywords: metabolomics,LC-MS,alignment,optimal transport,cross-study
Author: Chiraag
Author-email: Chiraag <37530396+chi-raag@users.noreply.github.com>
License: # MIT License
Classifier: Programming Language :: Python :: 3
Classifier: Programming Language :: Python :: 3 :: Only
Classifier: License :: OSI Approved :: MIT License
Classifier: Operating System :: OS Independent
Classifier: Intended Audience :: Science/Research
Classifier: Topic :: Scientific/Engineering :: Bio-Informatics
Requires-Dist: numpy
Requires-Dist: pandas
Requires-Dist: scipy
Requires-Dist: scikit-learn
Requires-Dist: pyyaml
Requires-Python: >=3.10
Project-URL: Documentation, https://github.com/omicsEye/massSight/tree/main/docs
Project-URL: Homepage, https://github.com/omicsEye/massSight
Project-URL: Issues, https://github.com/omicsEye/massSight/issues
Project-URL: Repository, https://github.com/omicsEye/massSight
